Workbook

Sheet Hypothèses
A1: TOPO3D GUADELOUPE — BUSINESS PLAN
A2: Prévisionnel de chiffre d'affaires — Mars 2026
A4: MARCHÉ CIBLE
A5: Cabinets d'architecture Guadeloupe | B5: 150 | C5: Source: Ordre des Architectes 971
A6: Bureaux d'études techniques | B6: 80 | C6: Source: estimation marché local
A7: Promoteurs immobiliers actifs | B7: 30 | C7: Source: estimation marché local
A8: Géomètres-experts | B8: 25 | C8: Source: OGE Guadeloupe
A9: Particuliers investisseurs (via KCI) | B9: 200 | C9: Source: base prospects KCI
A10: TOTAL PROSPECTS | B10: =SUM(B5:B9) -> 485
A12: TARIFICATION
A13: Offre | B13: Prix (€) | C13: Contenu
A14: Essentiel | B14: 49 | C14: Mesh OBJ 5m + GeoJSON
A15: Complet (offre phare) | B15: 99 | C15: OBJ 2-3m + DXF courbes + rapport
A16: Pro Illimité (mensuel) | B16: 249 | C16: Abonnement illimité + API
A19: HYPOTHÈSES DE CONVERSION
A20: Taux de conversion Essentiel (an 1) | B20: 0.05 | C20: 5% du marché cible
A21: Taux de conversion Complet (an 1) | B21: 0.08 | C21: 8% — offre phare
A22: Taux de conversion Pro (an 1) | B22: 0.02 | C22: 2% — abonnement mensuel
A23: Croissance annuelle du taux de conversion | B23: 0.5 | C23: 50%/an (notoriété)
A24: Fréquence commandes Essentiel (par client/an) | B24: 3 | C24: 3 parcelles/an
A25: Fréquence commandes Complet (par client/an) | B25: 5 | C25: 5 parcelles/an
A26: Coût variable par génération | B26: 2 | C26: API + compute
A27: Charges fixes mensuelles | B27: 50 | C27: Hébergement Vercel + domaine

Sheet Prévisionnel CA
A1: PRÉVISIONNEL CHIFFRE D'AFFAIRES — TOPO3D GUADELOUPE
A2: Projection sur 3 ans (2026-2028)
B4: Année 1 (2026) | C4: Année 2 (2027) | D4: Année 3 (2028) | E4: Total 3 ans
A5: CLIENTS ACQUIS | B5: =ROUND(Hypothèses!B20*Hypothèses!B10,0) -> 24 | C5: =ROUND(B5*(1+Hypothèses!B23),0) -> 36 | D5: =ROUND(C5*(1+Hypothèses!B23),0) -> 54 | E5: =SUM(B5:D5) -> 114
A6: Essentiel (taux × marché) | B6: =ROUND(Hypothèses!B21*Hypothèses!B10,0) -> 39 | C6: =ROUND(B6*(1+Hypothèses!B23),0) -> 59 | D6: =ROUND(C6*(1+Hypothèses!B23),0) -> 89 | E6: =SUM(B6:D6) -> 187
A7: Complet (taux × marché) | B7: =ROUND(Hypothèses!B22*Hypothèses!B10,0) -> 10 | C7: =ROUND(B7*(1+Hypothèses!B23),0) -> 15 | D7: =ROUND(C7*(1+Hypothèses!B23),0) -> 23 | E7: =SUM(B7:D7) -> 48
A8: Pro abonnés | B8: =SUM(B5:B7) -> 73 | C8: =SUM(C5:C7) -> 110 | D8: =SUM(D5:D7) -> 166 | E8: =SUM(B8:D8) -> 349
A9: Total clients
A11: VOLUME DE COMMANDES | B11: =B5*Hypothèses!B24 -> 72 | C11: =C5*Hypothèses!B24 -> 108 | D11: =D5*Hypothèses!B24 -> 162 | E11: =SUM(B11:D11) -> 342
A12: Commandes Essentiel | B12: =B6*Hypothèses!B25 -> 195 | C12: =C6*Hypothèses!B25 -> 295 | D12: =D6*Hypothèses!B25 -> 445 | E12: =SUM(B12:D12) -> 935
A13: Commandes Complet | B13: =B7*12 -> 120 | C13: =C7*12 -> 180 | D13: =D7*12 -> 276 | E13: =SUM(B13:D13) -> 576
A14: Mois abonnement Pro | B14: =SUM(B11:B13) -> 387 | C14: =SUM(C11:C13) -> 583 | D14: =SUM(D11:D13) -> 883 | E14: =SUM(B14:D14) -> 1853
A15: Total commandes
A17: CHIFFRE D'AFFAIRES | B17: =B11*Hypothèses!B14 -> 3528 | C17: =C11*Hypothèses!B14 -> 5292 | D17: =D11*Hypothèses!B14 -> 7938 | E17: =SUM(B17:D17) -> 16758
A18: CA Essentiel | B18: =B12*Hypothèses!B15 -> 19305 | C18: =C12*Hypothèses!B15 -> 29205 | D18: =D12*Hypothèses!B15 -> 44055 | E18: =SUM(B18:D18) -> 92565
A19: CA Complet | B19: =B13*Hypothèses!B16 -> 29880 | C19: =C13*Hypothèses!B16 -> 44820 | D19: =D13*Hypothèses!B16 -> 68724 | E19: =SUM(B19:D19) -> 143424
A20: CA Pro (abonnements) | B20: =SUM(B17:B19) -> 52713 | C20: =SUM(C17:C19) -> 79317 | D20: =SUM(D17:D19) -> 120717 | E20: =SUM(B20:D20) -> 252747
A21: CA TOTAL
A23: COÛTS | B23: =(B11+B12)*Hypothèses!B26 -> 534 | C23: =(C11+C12)*Hypothèses!B26 -> 806 | D23: =(D11+D12)*Hypothèses!B26 -> 1214 | E23: =SUM(B23:D23) -> 2554
A24: Coûts variables | B24: =Hypothèses!B27*12 -> 600 | C24: =Hypothèses!B27*12 -> 600 | D24: =Hypothèses!B27*12 -> 600 | E24: =SUM(B24:D24) -> 1800
A25: Charges fixes | B25: =B23+B24 -> 1134 | C25: =C23+C24 -> 1406 | D25: =D23+D24 -> 1814 | E25: =SUM(B25:D25) -> 4354
A26: Total coûts
A28: MARGE | B28: =B20-B25 -> 51579 | C28: =C20-C25 -> 77911 | D28: =D20-D25 -> 118903 | E28: =SUM(B28:D28) -> 248393
A29: Marge brute | B29: =IF(B20>0,B28/B20,0) -> 0.97848728 | C29: =IF(C20>0,C28/C20,0) -> 0.98227366 | D29: =IF(D20>0,D28/D20,0) -> 0.98497312 | E29: =IF(E20>0,E28/E20,0) -> 0.98277329
A30: Taux de marge
